gelee/__init__.py
gelee/__main__.py
gelee/cli.py
gelee/gelee.py
tests/__init__.py
tests/context.py
tests/test_cli.py
tests/test_gelee.py
gelee-2021.10.24.dist-info/LICENSE
gelee-2021.10.24.dist-info/METADATA
gelee-2021.10.24.dist-info/WHEEL
gelee-2021.10.24.dist-info/entry_points.txt
gelee-2021.10.24.dist-info/top_level.txt
gelee-2021.10.24.dist-info/RECORD
