Metadata-Version: 2.1
Name: gelee
Version: 2021.10.24
Summary: Configuration format validator for CSV, INI, JSON, TOML, XML, and YAML.
Home-page: https://github.com/sthagen/gelee
Author: Stefan Hagen
Author-email: stefan@hagen.link
Maintainer: Stefan Hagen
Maintainer-email: stefan@hagen.link
License: UNKNOWN
Project-URL: Bug Tracker, https://github.com/sthagen/gelee/issues
Project-URL: Documentation, https://sthagen.github.io/gelee
Project-URL: Source Code, https://github.com/sthagen/gelee
Keywords: csv,developer-tools,ini-files,json,lint,toml,xml,yaml,validation
Platform: UNKNOWN
Classifier: Development Status :: 4 - Beta
Classifier: Intended Audience :: Developers
Classifier: License :: OSI Approved :: MIT License
Classifier: Programming Language :: Python :: 3.10
Classifier: Programming Language :: Python :: 3.8
Classifier: Programming Language :: Python :: 3.9
Requires-Python: >=3.8
Requires-Dist: jmespath (>=0.10.0)
Requires-Dist: jsonschema (>=4.1.2)
Requires-Dist: lxml (>=4.6.3)
Requires-Dist: pyyaml (>=6.0)
Requires-Dist: toml (>=0.10.2)
Requires-Dist: typer (>=0.4.0)
Requires-Dist: xmlschema (>=1.8.1)
Provides-Extra: dev
Requires-Dist: black ; extra == 'dev'
Requires-Dist: coverage ; extra == 'dev'
Requires-Dist: flake8 ; extra == 'dev'
Requires-Dist: mypy ; extra == 'dev'
Requires-Dist: pytest ; extra == 'dev'
Requires-Dist: pytest-cov ; extra == 'dev'
Requires-Dist: pytest-flake8 ; extra == 'dev'
